edgebrain/__init__.py
edgebrain/core/__init__.py
edgebrain/core/agent.py
edgebrain/core/cli.py
edgebrain/core/orchestrator.py
edgebrain/integration/__init__.py
edgebrain/integration/ollama_client.py
edgebrain/memory/__init__.py
edgebrain/memory/memory_manager.py
edgebrain/tools/__init__.py
edgebrain/tools/tool_registry.py
edgebrain-0.1.3.dist-info/licenses/LICENSE
edgebrain-0.1.3.dist-info/METADATA
edgebrain-0.1.3.dist-info/WHEEL
edgebrain-0.1.3.dist-info/entry_points.txt
edgebrain-0.1.3.dist-info/top_level.txt
edgebrain-0.1.3.dist-info/RECORD
