Metadata-Version: 2.4
Name: edgebrain
Version: 0.1.3
Summary: An open-source agentic framework for building AI agents with Ollama-based models
Home-page: https://github.com/madnansultandotme/edgebrain.git
Author: Muhammad Adnan Sultan
Author-email: info.adnansultan@gmail.com
Classifier: Development Status :: 3 - Alpha
Classifier: Intended Audience :: Developers
Classifier: License :: OSI Approved :: MIT License
Classifier: Operating System :: OS Independent
Classifier: Programming Language :: Python :: 3
Classifier: Programming Language :: Python :: 3.8
Classifier: Programming Language :: Python :: 3.9
Classifier: Programming Language :: Python :: 3.10
Classifier: Programming Language :: Python :: 3.11
Requires-Python: >=3.8
License-File: LICENSE
Requires-Dist: aiohappyeyeballs==2.6.1
Requires-Dist: aiohttp==3.12.13
Requires-Dist: aiosignal==1.3.2
Requires-Dist: annotated-types==0.7.0
Requires-Dist: anyio==4.9.0
Requires-Dist: asyncio==3.4.3
Requires-Dist: attrs==25.3.0
Requires-Dist: backoff==2.2.1
Requires-Dist: bcrypt==4.3.0
Requires-Dist: build==1.2.2.post1
Requires-Dist: cachetools==5.5.2
Requires-Dist: certifi==2025.6.15
Requires-Dist: charset-normalizer==3.4.2
Requires-Dist: chromadb==1.0.13
Requires-Dist: click==8.2.1
Requires-Dist: colorama==0.4.6
Requires-Dist: coloredlogs==15.0.1
Requires-Dist: distro==1.9.0
Requires-Dist: durationpy==0.10
Requires-Dist: filelock==3.18.0
Requires-Dist: flatbuffers==25.2.10
Requires-Dist: frozenlist==1.7.0
Requires-Dist: fsspec==2025.5.1
Requires-Dist: google-auth==2.40.3
Requires-Dist: googleapis-common-protos==1.70.0
Requires-Dist: grpcio==1.73.1
Requires-Dist: h11==0.16.0
Requires-Dist: httpcore==1.0.9
Requires-Dist: httptools==0.6.4
Requires-Dist: httpx==0.28.1
Requires-Dist: huggingface-hub==0.33.1
Requires-Dist: humanfriendly==10.0
Requires-Dist: idna==3.10
Requires-Dist: importlib_metadata==8.7.0
Requires-Dist: importlib_resources==6.5.2
Requires-Dist: iniconfig==2.1.0
Requires-Dist: jsonschema==4.24.0
Requires-Dist: jsonschema-specifications==2025.4.1
Requires-Dist: kubernetes==33.1.0
Requires-Dist: markdown-it-py==3.0.0
Requires-Dist: mdurl==0.1.2
Requires-Dist: mmh3==5.1.0
Requires-Dist: mpmath==1.3.0
Requires-Dist: multidict==6.6.0
Requires-Dist: numpy==2.3.1
Requires-Dist: oauthlib==3.3.1
Requires-Dist: ollama==0.5.1
Requires-Dist: onnxruntime==1.22.0
Requires-Dist: opentelemetry-api==1.34.1
Requires-Dist: opentelemetry-exporter-otlp-proto-common==1.34.1
Requires-Dist: opentelemetry-exporter-otlp-proto-grpc==1.34.1
Requires-Dist: opentelemetry-proto==1.34.1
Requires-Dist: opentelemetry-sdk==1.34.1
Requires-Dist: opentelemetry-semantic-conventions==0.55b1
Requires-Dist: orjson==3.10.18
Requires-Dist: overrides==7.7.0
Requires-Dist: packaging==25.0
Requires-Dist: pluggy==1.6.0
Requires-Dist: posthog==6.0.0
Requires-Dist: propcache==0.3.2
Requires-Dist: protobuf==5.29.5
Requires-Dist: pyasn1==0.6.1
Requires-Dist: pyasn1_modules==0.4.2
Requires-Dist: pybase64==1.4.1
Requires-Dist: pydantic==2.11.7
Requires-Dist: pydantic_core==2.33.2
Requires-Dist: Pygments==2.19.2
Requires-Dist: PyPika==0.48.9
Requires-Dist: pyproject_hooks==1.2.0
Requires-Dist: pyreadline3==3.5.4
Requires-Dist: pytest==8.4.1
Requires-Dist: pytest-asyncio==1.0.0
Requires-Dist: python-dateutil==2.9.0.post0
Requires-Dist: python-dotenv==1.1.1
Requires-Dist: PyYAML==6.0.2
Requires-Dist: referencing==0.36.2
Requires-Dist: requests==2.32.4
Requires-Dist: requests-oauthlib==2.0.0
Requires-Dist: rich==14.0.0
Requires-Dist: rpds-py==0.25.1
Requires-Dist: rsa==4.9.1
Requires-Dist: setuptools==80.9.0
Requires-Dist: shellingham==1.5.4
Requires-Dist: six==1.17.0
Requires-Dist: sniffio==1.3.1
Requires-Dist: sympy==1.14.0
Requires-Dist: tenacity==9.1.2
Requires-Dist: tokenizers==0.21.2
Requires-Dist: tqdm==4.67.1
Requires-Dist: typer==0.16.0
Requires-Dist: typing-inspection==0.4.1
Requires-Dist: typing_extensions==4.14.0
Requires-Dist: urllib3==2.5.0
Requires-Dist: uvicorn==0.34.3
Requires-Dist: watchfiles==1.1.0
Requires-Dist: websocket-client==1.8.0
Requires-Dist: websockets==15.0.1
Requires-Dist: yarl==1.20.1
Requires-Dist: zipp==3.23.0
Provides-Extra: dev
Requires-Dist: pytest>=7.0.0; extra == "dev"
Requires-Dist: pytest-asyncio>=0.21.0; extra == "dev"
Requires-Dist: black>=23.0.0; extra == "dev"
Requires-Dist: flake8>=6.0.0; extra == "dev"
Requires-Dist: mypy>=1.0.0; extra == "dev"
Dynamic: author
Dynamic: author-email
Dynamic: classifier
Dynamic: description
Dynamic: description-content-type
Dynamic: home-page
Dynamic: license-file
Dynamic: provides-extra
Dynamic: requires-dist
Dynamic: requires-python
Dynamic: summary
